nphonecli/__init__.py
nphonecli/core.py
nphonecli-1.5.0.dist-info/licenses/LICENSE
nphonecli-1.5.0.dist-info/METADATA
nphonecli-1.5.0.dist-info/WHEEL
nphonecli-1.5.0.dist-info/top_level.txt
nphonecli-1.5.0.dist-info/RECORD
