Metadata-Version: 2.4
Name: nphonecli
Version: 1.5.0
Summary: nPhoneKIT as an interfaceable and easy-to-implement Python PyPI package.
Author-email: NlckySolutions <contact@nlckysolutions.org>
License:                     GNU GENERAL PUBLIC LICENSE
Project-URL: Homepage, https://github.com/nlckysolutions/nPhoneCLI
Project-URL: Issues, https://github.com/nlckysolutions/nPhoneCLI/issues
Keywords: nphonekit,android,fastboot,cli,phone,frp
Classifier: License :: OSI Approved :: GNU General Public License v3 (GPLv3)
Requires-Python: >=3.9
License-File: LICENSE
Requires-Dist: pyserial>=3.5
Dynamic: license-file
